Workbook
Name Slicer_Region: #N/A

Sheet PIVOT TABLE
A3: Region | B3: Sum of Total Revenue | D3: Average of NP | G3: Item Type | H3: Sum of Net Profit
A4: Asia | B4: 21335028 | D4: 440911.94 | G4: Baby Food | H4: 3697704
A5: Australia and Oceania | B5: 14075241 | G5: Beverages | H5: 808089
A6: Central America and the Caribbean | B6: 9165918 | D6: Region | E6: Sum of Units Sold | G6: Cereal | H6: 2187900.4
A7: Europe | B7: 32188083 | D7: Asia | E7: 59967 | G7: Clothes | H7: 4941881
A8: Middle East and North Africa | B8: 14043215 | D8: Australia and Oceania | E8: 68325 | G8: Cosmetics | H8: 13838585
A9: North America | B9: 5644770 | D9: Central America and the Caribbean | E9: 35771 | G9: Fruits | H9: 94996.2
A10: Sub-Saharan Africa | B10: 39652991 | D10: Europe | E10: 96338 | G10: Household | H10: 9011715.2
A11: Grand Total | B11: 136105246 | D11: Middle East and North Africa | E11: 48678 | G11: Meat | H11: 578051.25
D12: North America | E12: 19143 | G12: Office Supplies | H12: 5409003.6
A13: Region | B13: Sum of Total Cost | D13: Sub-Saharan Africa | E13: 182870 | G13: Personal Care | H13: 1156815
A14: Asia | B14: 15241636 | D14: Grand Total | E14: 511092 | G14: Socks | H14: 725488.4
A15: Australia and Oceania | B15: 9371508 | G15: Vegetables | H15: 1200052.3
A16: Central America and the Caribbean | B16: 6330463 | D16: Order Priority | E16: Sum of Total Revenue | G16: Grand Total | H16: 43650282
A17: Europe | B17: 21341292 | D17: C | E17: 18821578
A18: Middle East and North Africa | B18: 8285994 | D18: H | E18: 48722994
A19: North America | B19: 4192635 | D19: L | E19: 35452217
A20: Sub-Saharan Africa | B20: 25394053 | D20: M | E20: 33108457
A21: Grand Total | B21: 90157581 | D21: Grand Total | E21: 136105246
A23: Region | B23: Sum of Net Profit | D23: ORDER YEAR | E23: Sum of Net Profit
A24: Asia | B24: 5788722.4 | D24: 2010 | E24: 6286726.7
A25: Australia and Oceania | B25: 4468546.3 | D25: 2011 | E25: 4584006.5
A26: Central America and the Caribbean | B26: 2693682.2 | D26: 2012 | E26: 8735027.7
A27: Europe | B27: 10304451 | D27: 2013 | E27: 6376077
A28: Middle East and North Africa | B28: 5469359.9 | D28: 2014 | E28: 5346096.5
A29: North America | B29: 1379528.2 | D29: 2015 | E29: 3781324
A30: Sub-Saharan Africa | B30: 13545991 | D30: 2016 | E30: 4657676.1
A31: Grand Total | B31: 43650282 | D31: 2017 | E31: 3883347.3
D32: Grand Total | E32: 43650282
A33: Region | B33: Sum of Gross Profit
A34: Asia | B34: 6093392 | D34: Sales Channel | E34: Count of Net Profit
A35: Australia and Oceania | B35: 4703733 | D35: Offline | E35: 0.49494949
A36: Central America and the Caribbean | B36: 2835455 | D36: Online | E36: 0.50505051
A37: Europe | B37: 10846791 | D37: Grand Total | E37: 1
A38: Middle East and North Africa | B38: 5757221
A39: North America | B39: 1452135
A40: Sub-Saharan Africa | B40: 14258938
A41: Grand Total | B41: 45947665

Sheet Dashboard
B2: HIBRID STORES
E4: TOTAL REVENUE | I4: TOTAL GROSS PROFIT | M4: TOTAL NET PROFIT | Q4: AVERAGE NP
E6: =GETPIVOTDATA("Total Revenue",'PIVOT TABLE'!$A$3) -> 136105246 | I6: =GETPIVOTDATA("Gross Profit",'PIVOT TABLE'!$A$33) -> 45947665 | M6: =GETPIVOTDATA("Net Profit",'PIVOT TABLE'!$A$23) -> 43650282 | Q6: =GETPIVOTDATA("AverageNP",'PIVOT TABLE'!$D$3) -> 440911.94
B7: UNIT SOLD
B9: =GETPIVOTDATA("Units Sold",'PIVOT TABLE'!$D$6) -> 511092
B11: TOTAL COST
B13: =GETPIVOTDATA("Total Cost",'PIVOT TABLE'!$A$13) -> 90157581

Sheet Data Set
A1: Region | B1: Country | C1: Item Type | D1: Sales Channel | E1: Order Priority | F1: Order Date | G1: Order Year | H1: Order ID | I1: Ship Date | J1: Units Sold | K1: Unit Price | L1: Unit Cost | M1: Total Revenue | N1: Total Cost | O1: Gross Profit | P1: Net Profit | Q1: AverageNP
A2: Australia and Oceania | B2: Tuvalu | C2: Baby Food | D2: Offline | E2: H | F2: 40326 | G2: =YEAR(Table2[[#This Row],[Order Date]]) -> 2010 | H2: 669165933 | I2: 40356 | J2: 9925 | K2: 255 | L2: 159 | M2: =Table2[[#This Row],[Units Sold]]*Table2[[#This Row],[Unit Price]] -> 2530875 | N2: =Table2[[#This Row],[Unit Cost]]*Table2[[#This Row],[Units Sold]] -> 1578075 | O2: =Table2[[#This Row],[Total Revenue]]-Table2[[#This Row],[Total Cost]] -> 952800 | P2: =Table2[[#This Row],[Gross Profit]]*0.95 -> 905160 | Q2: =AVERAGE(Table2[Net Profit]) -> 440911.94
A3: Central America and the Caribbean | B3: Gre0da | C3: Cereal | D3: Online | E3: C | F3: 41143 | G3: =YEAR(Table2[[#This Row],[Order Date]]) -> 2012 | H3: 963881480 | I3: 41167 | J3: 2804 | K3: 206 | L3: 117 | M3: =Table2[[#This Row],[Units Sold]]*Table2[[#This Row],[Unit Price]] -> 577624 | N3: =Table2[[#This Row],[Unit Cost]]*Table2[[#This Row],[Units Sold]] -> 328068 | O3: =Table2[[#This Row],[Total Revenue]]-Table2[[#This Row],[Total Cost]] -> 249556 | P3: =Table2[[#This Row],[Gross Profit]]*0.95 -> 237078.2
A4: Sub-Saharan Africa | B4: Sao Tome and Principe | C4: Fruits | D4: Online | E4: C | F4: 41810 | G4: =YEAR(Table2[[#This Row],[Order Date]]) -> 2014 | H4: 514321792 | I4: 41766 | J4: 8102 | K4: 9 | L4: 7 | M4: =Table2[[#This Row],[Units Sold]]*Table2[[#This Row],[Unit Price]] -> 72918 | N4: =Table2[[#This Row],[Unit Cost]]*Table2[[#This Row],[Units Sold]] -> 56714 | O4: =Table2[[#This Row],[Total Revenue]]-Table2[[#This Row],[Total Cost]] -> 16204 | P4: =Table2[[#This Row],[Gross Profit]]*0.95 -> 15393.8
A5: Sub-Saharan Africa | B5: Rwanda | C5: Office Supplies | D5: Offline | E5: L | F5: 41306 | G5: =YEAR(Table2[[#This Row],[Order Date]]) -> 2013 | H5: 115456712 | I5: 41427 | J5: 5062 | K5: 651 | L5: 525 | M5: =Table2[[#This Row],[Units Sold]]*Table2[[#This Row],[Unit Price]] -> 3295362 | N5: =Table2[[#This Row],[Unit Cost]]*Table2[[#This Row],[Units Sold]] -> 2657550 | O5: =Table2[[#This Row],[Total Revenue]]-Table2[[#This Row],[Total Cost]] -> 637812 | P5: =Table2[[#This Row],[Gross Profit]]*0.95 -> 605921.4
A6: Australia and Oceania | B6: Solomon Islands | C6: Baby Food | D6: Online | E6: C | F6: 42039 | G6: =YEAR(Table2[[#This Row],[Order Date]]) -> 2015 | H6: 547995746 | I6: 42056 | J6: 2974 | K6: 255 | L6: 159 | M6: =Table2[[#This Row],[Units Sold]]*Table2[[#This Row],[Unit Price]] -> 758370 | N6: =Table2[[#This Row],[Unit Cost]]*Table2[[#This Row],[Units Sold]] -> 472866 | O6: =Table2[[#This Row],[Total Revenue]]-Table2[[#This Row],[Total Cost]] -> 285504 | P6: =Table2[[#This Row],[Gross Profit]]*0.95 -> 271228.8
A7: Sub-Saharan Africa | B7: Angola | C7: Household | D7: Offline | E7: M | F7: 40656 | G7: =YEAR(Table2[[#This Row],[Order Date]]) -> 2011 | H7: 135425221 | I7: 40660 | J7: 4187 | K7: 668 | L7: 0 | M7: =Table2[[#This Row],[Units Sold]]*Table2[[#This Row],[Unit Price]] -> 2796916 | N7: =Table2[[#This Row],[Unit Cost]]*Table2[[#This Row],[Units Sold]] -> 0 | O7: =Table2[[#This Row],[Total Revenue]]-Table2[[#This Row],[Total Cost]] -> 2796916 | P7: =Table2[[#This Row],[Gross Profit]]*0.95 -> 2657070.2
A8: Sub-Saharan Africa | B8: Burki Faso | C8: Vegetables | D8: Online | E8: H | F8: 41107 | G8: =YEAR(Table2[[#This Row],[Order Date]]) -> 2012 | H8: 871543967 | I8: 41117 | J8: 8082 | K8: 154 | L8: 91 | M8: =Table2[[#This Row],[Units Sold]]*Table2[[#This Row],[Unit Price]] -> 1244628 | N8: =Table2[[#This Row],[Unit Cost]]*Table2[[#This Row],[Units Sold]] -> 735462 | O8: =Table2[[#This Row],[Total Revenue]]-Table2[[#This Row],[Total Cost]] -> 509166 | P8: =Table2[[#This Row],[Gross Profit]]*0.95 -> 483707.7
A9: Sub-Saharan Africa | B9: Republic of the Congo | C9: Personal Care | D9: Offline | E9: M | F9: 42199 | G9: =YEAR(Table2[[#This Row],[Order Date]]) -> 2015 | H9: 770463311 | I9: 42241 | J9: 6070 | K9: 82 | L9: 57 | M9: =Table2[[#This Row],[Units Sold]]*Table2[[#This Row],[Unit Price]] -> 497740 | N9: =Table2[[#This Row],[Unit Cost]]*Table2[[#This Row],[Units Sold]] -> 345990 | O9: =Table2[[#This Row],[Total Revenue]]-Table2[[#This Row],[Total Cost]] -> 151750 | P9: =Table2[[#This Row],[Gross Profit]]*0.95 -> 144162.5
A10: Sub-Saharan Africa | B10: Senegal | C10: Cereal | D10: Online | E10: H | F10: 41747 | G10: =YEAR(Table2[[#This Row],[Order Date]]) -> 2014 | H10: 616607081 | I10: 41789 | J10: 6593 | K10: 206 | L10: 117 | M10: =Table2[[#This Row],[Units Sold]]*Table2[[#This Row],[Unit Price]] -> 1358158 | N10: =Table2[[#This Row],[Unit Cost]]*Table2[[#This Row],[Units Sold]] -> 771381 | O10: =Table2[[#This Row],[Total Revenue]]-Table2[[#This Row],[Total Cost]] -> 586777 | P10: =Table2[[#This Row],[Gross Profit]]*0.95 -> 557438.15
A11: Asia | B11: Kyrgyzstan | C11: Vegetables | D11: Online | E11: H | F11: 40718 | G11: =YEAR(Table2[[#This Row],[Order Date]]) -> 2011 | H11: 814711606 | I11: 40884 | J11: 124 | K11: 154 | L11: 91 | M11: =Table2[[#This Row],[Units Sold]]*Table2[[#This Row],[Unit Price]] -> 19096 | N11: =Table2[[#This Row],[Unit Cost]]*Table2[[#This Row],[Units Sold]] -> 11284 | O11: =Table2[[#This Row],[Total Revenue]]-Table2[[#This Row],[Total Cost]] -> 7812 | P11: =Table2[[#This Row],[Gross Profit]]*0.95 -> 7421.4
A12: Sub-Saharan Africa | B12: Cape Verde | C12: Clothes | D12: Offline | E12: H | F12: 41853 | G12: =YEAR(Table2[[#This Row],[Order Date]]) -> 2014 | H12: 939825713 | I12: 41870 | J12: 4168 | K12: 109 | L12: 36 | M12: =Table2[[#This Row],[Units Sold]]*Table2[[#This Row],[Unit Price]] -> 454312 | N12: =Table2[[#This Row],[Unit Cost]]*Table2[[#This Row],[Units Sold]] -> 150048 | O12: =Table2[[#This Row],[Total Revenue]]-Table2[[#This Row],[Total Cost]] -> 304264 | P12: =Table2[[#This Row],[Gross Profit]]*0.95 -> 289050.8
A13: Asia | B13: Bangladesh | C13: Clothes | D13: Online | E13: L | F13: 42748 | G13: =YEAR(Table2[[#This Row],[Order Date]]) -> 2017 | H13: 187310731 | I13: 42738 | J13: 8263 | K13: 109 | L13: 36 | M13: =Table2[[#This Row],[Units Sold]]*Table2[[#This Row],[Unit Price]] -> 900667 | N13: =Table2[[#This Row],[Unit Cost]]*Table2[[#This Row],[Units Sold]] -> 297468 | O13: =Table2[[#This Row],[Total Revenue]]-Table2[[#This Row],[Total Cost]] -> 603199 | P13: =Table2[[#This Row],[Gross Profit]]*0.95 -> 573039.05
A14: Central America and the Caribbean | B14: Honduras | C14: Household | D14: Offline | E14: H | F14: 42774 | G14: =YEAR(Table2[[#This Row],[Order Date]]) -> 2017 | H14: 522840487 | I14: 42779 | J14: 8974 | K14: 668 | L14: 503 | M14: =Table2[[#This Row],[Units Sold]]*Table2[[#This Row],[Unit Price]] -> 5994632 | N14: =Table2[[#This Row],[Unit Cost]]*Table2[[#This Row],[Units Sold]] -> 4513922 | O14: =Table2[[#This Row],[Total Revenue]]-Table2[[#This Row],[Total Cost]] -> 1480710 | P14: =Table2[[#This Row],[Gross Profit]]*0.95 -> 1406674.5
... A100: Sub-Saharan Africa | B100: Mozambique | C100: Household | D100: Offline | E100: L | F100: 40949 | G100: =YEAR(Table2[[#This Row],[Order Date]]) -> 2012 | H100: 665095412 | I100: 40954 | J100: 5367 | K100: 668 | L100: 503 | M100: =Table2[[#This Row],[Units Sold]]*Table2[[#This Row],[Unit Price]] -> 3585156 | N100: =Table2[[#This Row],[Unit Cost]]*Table2[[#This Row],[Units Sold]] -> 2699601 | O100: =Table2[[#This Row],[Total Revenue]]-Table2[[#This Row],[Total Cost]] -> 885555 | P100: =Table2[[#This Row],[Gross Profit]]*0.95 -> 841277.25
J101: =SUM(J2:J100) -> 511092 | M101: =SUM(M2:M100) -> 136105246 | N101: =SUM(N2:N100) -> 90157581 | O101: =SUM(O2:O100) -> 45947665 | P101: =SUBTOTAL(109,Table2[Net Profit]) -> 43650282
